vigilance/__init__.py
vigilance/cli.py
vigilance/configuration.py
vigilance/constraint.py
vigilance/error.py
vigilance/parser.py
vigilance/representation.py
vigilance/suite.py
vigilance/default_suites/__init__.py
vigilance/default_suites/cobertura.py
vigilance/default_suites/doxygen.py
vigilance/plugin/__init__.py
vigilance/plugin/tooling.py
vigilance-0.1.1.data/scripts/doxypy_filter
vigilance-0.1.1.dist-info/METADATA
vigilance-0.1.1.dist-info/RECORD
vigilance-0.1.1.dist-info/WHEEL
vigilance-0.1.1.dist-info/entry_points.txt
vigilance-0.1.1.dist-info/top_level.txt
